qsa/__init__.py
qsa/analysis.py
qsa/domain.py
qsa/graphics.py
qsa/measurement.py
qsa/rtxi.py
qsa-1.0.dist-info/LICENSE
qsa-1.0.dist-info/METADATA
qsa-1.0.dist-info/WHEEL
qsa-1.0.dist-info/top_level.txt
qsa-1.0.dist-info/RECORD
