Metadata-Version: 2.1
Name: qsa
Version: 1.0
Summary: Linear and Quadratic Analysis in the Frequency Domain
Home-page: http://openqsa.org
Author: Christophe Magnani
License: UNKNOWN
Platform: UNKNOWN
Classifier: Programming Language :: Python :: 3.7
Classifier: License :: OSI Approved :: GNU Lesser General Public License v3 or later (LGPLv3+)
Classifier: Topic :: Scientific/Engineering
Classifier: Programming Language :: Python :: 3.7
Classifier: Intended Audience :: Science/Research
Classifier: Development Status :: 1 - Planning
Requires-Dist: numpy
Requires-Dist: matplotlib
